dblpbib/__init__.py
dblpbib-0.0.2.dist-info/LICENSE
dblpbib-0.0.2.dist-info/METADATA
dblpbib-0.0.2.dist-info/WHEEL
dblpbib-0.0.2.dist-info/entry_points.txt
dblpbib-0.0.2.dist-info/top_level.txt
dblpbib-0.0.2.dist-info/RECORD
