Metadata-Version: 2.1
Name: dblpbib
Version: 0.0.2
Summary: Download all bibtex references for provided author
Home-page: UNKNOWN
Author: PG Drange
Author-email: Pal.Drange@uib.no
License: UNKNOWN
Platform: UNKNOWN
License-File: LICENSE
Requires-Dist: requests
